CHANGELOG.md
django_compressor_js/__init__.py
django_compressor_js/precompilers.py
django_compressor_js-0.1.0.dist-info/WHEEL
django_compressor_js-0.1.0.dist-info/METADATA
django_compressor_js-0.1.0.dist-info/RECORD
