Metadata-Version: 2.1
Name: django-compressor-js
Version: 0.1.0
Summary: Transpile JavaScript without running an extra node.js process.
Home-page: https://github.com/adamghill/django-compressor-js
License: MIT
Keywords: django,django-compressor,babel,javascript
Author: Adam Hill
Author-email: adamghill@yahoo.com
Requires-Python: >=3.6,<4.0
Classifier: License :: OSI Approved :: MIT License
Classifier: Programming Language :: Python :: 3
Classifier: Programming Language :: Python :: 3.6
Classifier: Programming Language :: Python :: 3.7
Classifier: Programming Language :: Python :: 3.8
Requires-Dist: django-compressor (>=2.4,<3.0)
Requires-Dist: dukpy (>=0.2.2,<0.3.0)
Project-URL: Repository, https://github.com/adamghill/django-compressor-js
